vuer_envs/.DS_Store
vuer_envs/__init__.py
vuer_envs/utility.py
vuer_envs/__pycache__/__init__.cpython-311.pyc
vuer_envs/__pycache__/__init__.cpython-38.pyc
vuer_envs/__pycache__/utility.cpython-311.pyc
vuer_envs/__pycache__/utility.cpython-38.pyc
vuer_envs/schemas/__init__.py
vuer_envs/schemas/base.py
vuer_envs/schemas/functional.py
vuer_envs/schemas/mujoco_schema.py
vuer_envs/schemas/schema.py
vuer_envs/schemas/__pycache__/__init__.cpython-311.pyc
vuer_envs/schemas/__pycache__/__init__.cpython-38.pyc
vuer_envs/schemas/__pycache__/base.cpython-311.pyc
vuer_envs/schemas/__pycache__/base.cpython-38.pyc
vuer_envs/schemas/__pycache__/functional.cpython-311.pyc
vuer_envs/schemas/__pycache__/functional.cpython-38.pyc
vuer_envs/schemas/__pycache__/mujoco_schema.cpython-311.pyc
vuer_envs/schemas/__pycache__/mujoco_schema.cpython-38.pyc
vuer_envs/schemas/__pycache__/scene_components.cpython-38.pyc
vuer_envs/schemas/__pycache__/schema.cpython-38.pyc
vuer_envs/schemas/robot_xmls/__init__.py
vuer_envs/schemas/robot_xmls/panda.py
vuer_envs/schemas/robot_xmls/robot_schema.py
vuer_envs/schemas/robot_xmls/robotiq.py
vuer_envs/schemas/robot_xmls/tomika_gripper.py
vuer_envs/schemas/robot_xmls/__pycache__/__init__.cpython-311.pyc
vuer_envs/schemas/robot_xmls/__pycache__/__init__.cpython-38.pyc
vuer_envs/schemas/robot_xmls/__pycache__/panda.cpython-311.pyc
vuer_envs/schemas/robot_xmls/__pycache__/panda.cpython-38.pyc
vuer_envs/schemas/robot_xmls/__pycache__/robot_schema.cpython-311.pyc
vuer_envs/schemas/robot_xmls/__pycache__/robot_schema.cpython-38.pyc
vuer_envs/schemas/robot_xmls/__pycache__/tomika_gripper.cpython-38.pyc
vuer_envs/schemas/room_xmls/__init__.py
vuer_envs/schemas/room_xmls/room_1.py
vuer_envs/schemas/room_xmls/__pycache__/__init__.cpython-311.pyc
vuer_envs/schemas/room_xmls/__pycache__/__init__.cpython-38.pyc
vuer_envs/schemas/room_xmls/__pycache__/room_1.cpython-311.pyc
vuer_envs/schemas/room_xmls/__pycache__/room_1.cpython-38.pyc
vuer_envs/scripts/__init__.py
vuer_envs-0.0.3.dist-info/LICENSE
vuer_envs-0.0.3.dist-info/METADATA
vuer_envs-0.0.3.dist-info/WHEEL
vuer_envs-0.0.3.dist-info/entry_points.txt
vuer_envs-0.0.3.dist-info/top_level.txt
vuer_envs-0.0.3.dist-info/RECORD
